lbdict.py
lbdict-0.1.4.dist-info/DESCRIPTION.rst
lbdict-0.1.4.dist-info/METADATA
lbdict-0.1.4.dist-info/RECORD
lbdict-0.1.4.dist-info/WHEEL
lbdict-0.1.4.dist-info/metadata.json
lbdict-0.1.4.dist-info/top_level.txt
