Metadata-Version: 2.0
Name: lbdict
Version: 0.1.4
Summary: A class for storing the pixel values of letters.
Home-page: https://github.com/Jugbot/Letter-Bitmap-Dictionary
Author: Jugbot
Author-email: lucasp465@gmail.com
License: UNKNOWN
Keywords: bitmap font dictionary
Platform: UNKNOWN
Requires-Dist: pillow
Requires-Dist: numpy
